secret_diary-0.2.dist-info/DESCRIPTION.rst
secret_diary-0.2.dist-info/METADATA
secret_diary-0.2.dist-info/RECORD
secret_diary-0.2.dist-info/WHEEL
secret_diary-0.2.dist-info/entry_points.txt
secret_diary-0.2.dist-info/metadata.json
secret_diary-0.2.dist-info/top_level.txt
secretdiary/__init__.py
secretdiary/clients.py
secretdiary/code_aes.py
secretdiary/diary.py
secretdiary/main.py
secretdiary/test_diary.py
