Metadata-Version: 2.0
Name: secret-diary
Version: 0.2
Summary: Secret diary
Home-page: https://github.com/DanteOnline/secret-diary
Author: DanteOnline
Author-email: iamdanteonline@gmail.com
License: GNU General Public License v3.0
Keywords: diary,encrypt,secret
Platform: UNKNOWN
Requires-Dist: pycryptodome
Requires-Dist: pycryptodomex
